commutauto/VERSION
commutauto/__init__.py
commutauto/__main__.py
commutauto/constants.py
commutauto/exceptions.py
commutauto/retry.py
commutauto/booking_service/__init__.py
commutauto/booking_service/date_manager.py
commutauto/booking_service/flex.py
commutauto/booking_service/payload.py
commutauto/booking_service/retriers.py
commutauto/booking_service/station.py
commutauto/client/__init__.py
commutauto/client/auth_token.py
commutauto/client/client.py
commutauto/model/__init__.py
commutauto/model/flex.py
commutauto/model/flex_booking.py
commutauto/model/reservation.py
commutauto/model/station.py
commutauto-0.7.0.dist-info/METADATA
commutauto-0.7.0.dist-info/WHEEL
commutauto-0.7.0.dist-info/entry_points.txt
commutauto-0.7.0.dist-info/top_level.txt
commutauto-0.7.0.dist-info/RECORD
